[{"medium":"https:\/\/static.tvmaze.com\/uploads\/images\/medium_portrait\/277\/693293.jpg","original":"https:\/\/static.tvmaze.com\/uploads\/images\/original_untouched\/277\/693293.jpg"},{"medium":"https:\/\/static.tvmaze.com\/uploads\/images\/medium_portrait\/284\/711303.jpg","original":"https:\/\/static.tvmaze.com\/uploads\/images\/original_untouched\/284\/711303.jpg"},{"medium":"https:\/\/static.tvmaze.com\/uploads\/images\/medium_portrait\/379\/948045.jpg","original":"https:\/\/static.tvmaze.com\/uploads\/images\/original_untouched\/379\/948045.jpg"},{"medium":"https:\/\/static.tvmaze.com\/uploads\/images\/medium_portrait\/278\/696645.jpg","original":"https:\/\/static.tvmaze.com\/uploads\/images\/original_untouched\/278\/696645.jpg"},{"medium":"https:\/\/static.tvmaze.com\/uploads\/images\/medium_portrait\/299\/748854.jpg","original":"https:\/\/static.tvmaze.com\/uploads\/images\/original_untouched\/299\/748854.jpg"},{"medium":"https:\/\/static.tvmaze.com\/uploads\/images\/medium_portrait\/290\/727378.jpg","original":"https:\/\/static.tvmaze.com\/uploads\/images\/original_untouched\/290\/727378.jpg"},{"medium":"https:\/\/static.tvmaze.com\/uploads\/images\/medium_portrait\/319\/799196.jpg","original":"https:\/\/static.tvmaze.com\/uploads\/images\/original_untouched\/319\/799196.jpg"},{"medium":"https:\/\/static.tvmaze.com\/uploads\/images\/medium_portrait\/189\/473411.jpg","original":"https:\/\/static.tvmaze.com\/uploads\/images\/original_untouched\/189\/473411.jpg"},{"medium":"https:\/\/static.tvmaze.com\/uploads\/images\/medium_portrait\/189\/473411.jpg","original":"https:\/\/static.tvmaze.com\/uploads\/images\/original_untouched\/189\/473411.jpg"},{"medium":"https:\/\/static.tvmaze.com\/uploads\/images\/medium_portrait\/261\/653909.jpg","original":"https:\/\/static.tvmaze.com\/uploads\/images\/original_untouched\/261\/653909.jpg"},{"medium":"https:\/\/static.tvmaze.com\/uploads\/images\/medium_portrait\/291\/729467.jpg","original":"https:\/\/static.tvmaze.com\/uploads\/images\/original_untouched\/291\/729467.jpg"},{"medium":"https:\/\/static.tvmaze.com\/uploads\/images\/medium_portrait\/291\/729467.jpg","original":"https:\/\/static.tvmaze.com\/uploads\/images\/original_untouched\/291\/729467.jpg"},{"medium":"https:\/\/static.tvmaze.com\/uploads\/images\/medium_portrait\/292\/731348.jpg","original":"https:\/\/static.tvmaze.com\/uploads\/images\/original_untouched\/292\/731348.jpg"},{"medium":"https:\/\/static.tvmaze.com\/uploads\/images\/medium_portrait\/311\/778535.jpg","original":"https:\/\/static.tvmaze.com\/uploads\/images\/original_untouched\/311\/778535.jpg"},{"medium":"https:\/\/static.tvmaze.com\/uploads\/images\/medium_portrait\/354\/885295.jpg","original":"https:\/\/static.tvmaze.com\/uploads\/images\/original_untouched\/354\/885295.jpg"},{"medium":"https:\/\/static.tvmaze.com\/uploads\/images\/medium_portrait\/291\/728871.jpg","original":"https:\/\/static.tvmaze.com\/uploads\/images\/original_untouched\/291\/728871.jpg"},{"medium":"https:\/\/static.tvmaze.com\/uploads\/images\/medium_portrait\/291\/728871.jpg","original":"https:\/\/static.tvmaze.com\/uploads\/images\/original_untouched\/291\/728871.jpg"},{"medium":"https:\/\/static.tvmaze.com\/uploads\/images\/medium_portrait\/291\/728871.jpg","original":"https:\/\/static.tvmaze.com\/uploads\/images\/original_untouched\/291\/728871.jpg"},{"medium":"https:\/\/static.tvmaze.com\/uploads\/images\/medium_portrait\/291\/728871.jpg","original":"https:\/\/static.tvmaze.com\/uploads\/images\/original_untouched\/291\/728871.jpg"},{"medium":"https:\/\/static.tvmaze.com\/uploads\/images\/medium_portrait\/291\/728871.jpg","original":"https:\/\/static.tvmaze.com\/uploads\/images\/original_untouched\/291\/728871.jpg"},{"medium":"https:\/\/static.tvmaze.com\/uploads\/images\/medium_portrait\/291\/728871.jpg","original":"https:\/\/static.tvmaze.com\/uploads\/images\/original_untouched\/291\/728871.jpg"},{"medium":"https:\/\/static.tvmaze.com\/uploads\/images\/medium_portrait\/291\/728871.jpg","original":"https:\/\/static.tvmaze.com\/uploads\/images\/original_untouched\/291\/728871.jpg"},{"medium":"https:\/\/static.tvmaze.com\/uploads\/images\/medium_portrait\/289\/723599.jpg","original":"https:\/\/static.tvmaze.com\/uploads\/images\/original_untouched\/289\/723599.jpg"},{"medium":"https:\/\/static.tvmaze.com\/uploads\/images\/medium_portrait\/282\/706333.jpg","original":"https:\/\/static.tvmaze.com\/uploads\/images\/original_untouched\/282\/706333.jpg"},{"medium":"https:\/\/static.tvmaze.com\/uploads\/images\/medium_portrait\/296\/740635.jpg","original":"https:\/\/static.tvmaze.com\/uploads\/images\/original_untouched\/296\/740635.jpg"},{"medium":"https:\/\/static.tvmaze.com\/uploads\/images\/medium_portrait\/337\/844624.jpg","original":"https:\/\/static.tvmaze.com\/uploads\/images\/original_untouched\/337\/844624.jpg"},{"medium":"https:\/\/static.tvmaze.com\/uploads\/images\/medium_portrait\/337\/844624.jpg","original":"https:\/\/static.tvmaze.com\/uploads\/images\/original_untouched\/337\/844624.jpg"},{"medium":"https:\/\/static.tvmaze.com\/uploads\/images\/medium_portrait\/46\/115863.jpg","original":"https:\/\/static.tvmaze.com\/uploads\/images\/original_untouched\/46\/115863.jpg"},{"medium":"https:\/\/static.tvmaze.com\/uploads\/images\/medium_portrait\/46\/115876.jpg","original":"https:\/\/static.tvmaze.com\/uploads\/images\/original_untouched\/46\/115876.jpg"},{"medium":"https:\/\/static.tvmaze.com\/uploads\/images\/medium_portrait\/51\/129595.jpg","original":"https:\/\/static.tvmaze.com\/uploads\/images\/original_untouched\/51\/129595.jpg"},{"medium":"https:\/\/static.tvmaze.com\/uploads\/images\/medium_portrait\/51\/129595.jpg","original":"https:\/\/static.tvmaze.com\/uploads\/images\/original_untouched\/51\/129595.jpg"},{"medium":"https:\/\/static.tvmaze.com\/uploads\/images\/medium_portrait\/121\/302950.jpg","original":"https:\/\/static.tvmaze.com\/uploads\/images\/original_untouched\/121\/302950.jpg"},{"medium":"https:\/\/static.tvmaze.com\/uploads\/images\/medium_portrait\/133\/332875.jpg","original":"https:\/\/static.tvmaze.com\/uploads\/images\/original_untouched\/133\/332875.jpg"},{"medium":"https:\/\/static.tvmaze.com\/uploads\/images\/medium_portrait\/304\/762250.jpg","original":"https:\/\/static.tvmaze.com\/uploads\/images\/original_untouched\/304\/762250.jpg"},{"medium":"https:\/\/static.tvmaze.com\/uploads\/images\/medium_portrait\/357\/894788.jpg","original":"https:\/\/static.tvmaze.com\/uploads\/images\/original_untouched\/357\/894788.jpg"},{"medium":"https:\/\/static.tvmaze.com\/uploads\/images\/medium_portrait\/258\/645558.jpg","original":"https:\/\/static.tvmaze.com\/uploads\/images\/original_untouched\/258\/645558.jpg"},{"medium":"https:\/\/static.tvmaze.com\/uploads\/images\/medium_portrait\/383\/957789.jpg","original":"https:\/\/static.tvmaze.com\/uploads\/images\/original_untouched\/383\/957789.jpg"},{"medium":"https:\/\/static.tvmaze.com\/uploads\/images\/medium_portrait\/299\/749765.jpg","original":"https:\/\/static.tvmaze.com\/uploads\/images\/original_untouched\/299\/749765.jpg"},{"medium":"https:\/\/static.tvmaze.com\/uploads\/images\/medium_portrait\/273\/683972.jpg","original":"https:\/\/static.tvmaze.com\/uploads\/images\/original_untouched\/273\/683972.jpg"},{"medium":"https:\/\/static.tvmaze.com\/uploads\/images\/medium_portrait\/285\/713040.jpg","original":"https:\/\/static.tvmaze.com\/uploads\/images\/original_untouched\/285\/713040.jpg"},{"medium":"https:\/\/static.tvmaze.com\/uploads\/images\/medium_portrait\/285\/713040.jpg","original":"https:\/\/static.tvmaze.com\/uploads\/images\/original_untouched\/285\/713040.jpg"},{"medium":"https:\/\/static.tvmaze.com\/uploads\/images\/medium_portrait\/288\/721432.jpg","original":"https:\/\/static.tvmaze.com\/uploads\/images\/original_untouched\/288\/721432.jpg"},{"medium":"https:\/\/static.tvmaze.com\/uploads\/images\/medium_portrait\/288\/721432.jpg","original":"https:\/\/static.tvmaze.com\/uploads\/images\/original_untouched\/288\/721432.jpg"},{"medium":"https:\/\/static.tvmaze.com\/uploads\/images\/medium_portrait\/288\/721715.jpg","original":"https:\/\/static.tvmaze.com\/uploads\/images\/original_untouched\/288\/721715.jpg"},{"medium":"https:\/\/static.tvmaze.com\/uploads\/images\/medium_portrait\/289\/723488.jpg","original":"https:\/\/static.tvmaze.com\/uploads\/images\/original_untouched\/289\/723488.jpg"},{"medium":"https:\/\/static.tvmaze.com\/uploads\/images\/medium_portrait\/289\/723488.jpg","original":"https:\/\/static.tvmaze.com\/uploads\/images\/original_untouched\/289\/723488.jpg"},{"medium":"https:\/\/static.tvmaze.com\/uploads\/images\/medium_portrait\/290\/727385.jpg","original":"https:\/\/static.tvmaze.com\/uploads\/images\/original_untouched\/290\/727385.jpg"},{"medium":"https:\/\/static.tvmaze.com\/uploads\/images\/medium_portrait\/290\/727385.jpg","original":"https:\/\/static.tvmaze.com\/uploads\/images\/original_untouched\/290\/727385.jpg"},{"medium":"https:\/\/static.tvmaze.com\/uploads\/images\/medium_portrait\/290\/727385.jpg","original":"https:\/\/static.tvmaze.com\/uploads\/images\/original_untouched\/290\/727385.jpg"},{"medium":"https:\/\/static.tvmaze.com\/uploads\/images\/medium_portrait\/290\/727385.jpg","original":"https:\/\/static.tvmaze.com\/uploads\/images\/original_untouched\/290\/727385.jpg"},{"medium":"https:\/\/static.tvmaze.com\/uploads\/images\/medium_portrait\/292\/730355.jpg","original":"https:\/\/static.tvmaze.com\/uploads\/images\/original_untouched\/292\/730355.jpg"},{"medium":"https:\/\/static.tvmaze.com\/uploads\/images\/medium_portrait\/292\/731984.jpg","original":"https:\/\/static.tvmaze.com\/uploads\/images\/original_untouched\/292\/731984.jpg"},{"medium":"https:\/\/static.tvmaze.com\/uploads\/images\/medium_portrait\/292\/731984.jpg","original":"https:\/\/static.tvmaze.com\/uploads\/images\/original_untouched\/292\/731984.jpg"},{"medium":"https:\/\/static.tvmaze.com\/uploads\/images\/medium_portrait\/297\/743345.jpg","original":"https:\/\/static.tvmaze.com\/uploads\/images\/original_untouched\/297\/743345.jpg"},{"medium":"https:\/\/static.tvmaze.com\/uploads\/images\/medium_portrait\/370\/926754.jpg","original":"https:\/\/static.tvmaze.com\/uploads\/images\/original_untouched\/370\/926754.jpg"},{"medium":"https:\/\/static.tvmaze.com\/uploads\/images\/medium_portrait\/406\/1015108.jpg","original":"https:\/\/static.tvmaze.com\/uploads\/images\/original_untouched\/406\/1015108.jpg"},{"medium":"https:\/\/static.tvmaze.com\/uploads\/images\/medium_portrait\/288\/720502.jpg","original":"https:\/\/static.tvmaze.com\/uploads\/images\/original_untouched\/288\/720502.jpg"},{"medium":"https:\/\/static.tvmaze.com\/uploads\/images\/medium_portrait\/59\/148354.jpg","original":"https:\/\/static.tvmaze.com\/uploads\/images\/original_untouched\/59\/148354.jpg"},{"medium":"https:\/\/static.tvmaze.com\/uploads\/images\/medium_portrait\/272\/681431.jpg","original":"https:\/\/static.tvmaze.com\/uploads\/images\/original_untouched\/272\/681431.jpg"},{"medium":"https:\/\/static.tvmaze.com\/uploads\/images\/medium_portrait\/365\/913800.jpg","original":"https:\/\/static.tvmaze.com\/uploads\/images\/original_untouched\/365\/913800.jpg"},{"medium":"https:\/\/static.tvmaze.com\/uploads\/images\/medium_portrait\/285\/713504.jpg","original":"https:\/\/static.tvmaze.com\/uploads\/images\/original_untouched\/285\/713504.jpg"},{"medium":"https:\/\/static.tvmaze.com\/uploads\/images\/medium_portrait\/332\/830481.jpg","original":"https:\/\/static.tvmaze.com\/uploads\/images\/original_untouched\/332\/830481.jpg"},{"medium":"https:\/\/static.tvmaze.com\/uploads\/images\/medium_portrait\/291\/727584.jpg","original":"https:\/\/static.tvmaze.com\/uploads\/images\/original_untouched\/291\/727584.jpg"},{"medium":"https:\/\/static.tvmaze.com\/uploads\/images\/medium_portrait\/291\/727584.jpg","original":"https:\/\/static.tvmaze.com\/uploads\/images\/original_untouched\/291\/727584.jpg"},{"medium":"https:\/\/static.tvmaze.com\/uploads\/images\/medium_portrait\/291\/727584.jpg","original":"https:\/\/static.tvmaze.com\/uploads\/images\/original_untouched\/291\/727584.jpg"},{"medium":"https:\/\/static.tvmaze.com\/uploads\/images\/medium_portrait\/291\/727584.jpg","original":"https:\/\/static.tvmaze.com\/uploads\/images\/original_untouched\/291\/727584.jpg"}]