[{"average":null},{"average":null},{"average":null},{"average":null},{"average":null},{"average":null},{"average":null},{"average":null},{"average":null},{"average":null},{"average":null},{"average":null},{"average":null},{"average":null},{"average":null},{"average":null},{"average":null},{"average":null},{"average":null},{"average":null},{"average":null},{"average":null},{"average":null},{"average":null},{"average":null},{"average":null},{"average":null},{"average":null},{"average":null},{"average":null},{"average":null},{"average":null},{"average":8.5},{"average":null},{"average":null},{"average":9.2},{"average":null},{"average":null},{"average":null},{"average":null},{"average":null},{"average":null},{"average":null},{"average":null},{"average":null},{"average":null},{"average":null},{"average":null},{"average":8},{"average":null},{"average":null},{"average":null},{"average":null},{"average":null},{"average":null},{"average":null},{"average":null},{"average":null},{"average":null},{"average":null},{"average":null},{"average":null},{"average":null},{"average":null},{"average":7.5},{"average":null},{"average":null},{"average":null},{"average":null},{"average":null},{"average":null},{"average":null},{"average":null},{"average":8.5},{"average":null},{"average":null},{"average":null},{"average":null},{"average":null},{"average":null},{"average":null},{"average":8.2},{"average":8.3},{"average":3.7},{"average":null},{"average":null}]