[{"self":{"href":"https:\/\/api.tvmaze.com\/episodes\/1982403"}},{"self":{"href":"https:\/\/api.tvmaze.com\/episodes\/1982404"}},{"self":{"href":"https:\/\/api.tvmaze.com\/episodes\/2140387"}},{"self":{"href":"https:\/\/api.tvmaze.com\/episodes\/1945592"}},{"self":{"href":"https:\/\/api.tvmaze.com\/episodes\/2065442"}},{"self":{"href":"https:\/\/api.tvmaze.com\/episodes\/2071477"}},{"self":{"href":"https:\/\/api.tvmaze.com\/episodes\/2071478"}},{"self":{"href":"https:\/\/api.tvmaze.com\/episodes\/2080225"}},{"self":{"href":"https:\/\/api.tvmaze.com\/episodes\/1977322"}},{"self":{"href":"https:\/\/api.tvmaze.com\/episodes\/2003096"}},{"self":{"href":"https:\/\/api.tvmaze.com\/episodes\/2264938"}},{"self":{"href":"https:\/\/api.tvmaze.com\/episodes\/2264939"}},{"self":{"href":"https:\/\/api.tvmaze.com\/episodes\/2264940"}},{"self":{"href":"https:\/\/api.tvmaze.com\/episodes\/2264941"}},{"self":{"href":"https:\/\/api.tvmaze.com\/episodes\/2264942"}},{"self":{"href":"https:\/\/api.tvmaze.com\/episodes\/1984176"}},{"self":{"href":"https:\/\/api.tvmaze.com\/episodes\/1984172"}},{"self":{"href":"https:\/\/api.tvmaze.com\/episodes\/1972058"}},{"self":{"href":"https:\/\/api.tvmaze.com\/episodes\/1985759"}},{"self":{"href":"https:\/\/api.tvmaze.com\/episodes\/1979332"}},{"self":{"href":"https:\/\/api.tvmaze.com\/episodes\/1979333"}},{"self":{"href":"https:\/\/api.tvmaze.com\/episodes\/1975597"}},{"self":{"href":"https:\/\/api.tvmaze.com\/episodes\/1985637"}},{"self":{"href":"https:\/\/api.tvmaze.com\/episodes\/1985638"}},{"self":{"href":"https:\/\/api.tvmaze.com\/episodes\/1985639"}},{"self":{"href":"https:\/\/api.tvmaze.com\/episodes\/1985640"}},{"self":{"href":"https:\/\/api.tvmaze.com\/episodes\/1985641"}},{"self":{"href":"https:\/\/api.tvmaze.com\/episodes\/1985642"}},{"self":{"href":"https:\/\/api.tvmaze.com\/episodes\/1985643"}},{"self":{"href":"https:\/\/api.tvmaze.com\/episodes\/1985644"}},{"self":{"href":"https:\/\/api.tvmaze.com\/episodes\/1985645"}},{"self":{"href":"https:\/\/api.tvmaze.com\/episodes\/1985646"}},{"self":{"href":"https:\/\/api.tvmaze.com\/episodes\/1985647"}},{"self":{"href":"https:\/\/api.tvmaze.com\/episodes\/1985648"}},{"self":{"href":"https:\/\/api.tvmaze.com\/episodes\/2176131"}},{"self":{"href":"https:\/\/api.tvmaze.com\/episodes\/2054911"}},{"self":{"href":"https:\/\/api.tvmaze.com\/episodes\/1985630"}},{"self":{"href":"https:\/\/api.tvmaze.com\/episodes\/1986135"}},{"self":{"href":"https:\/\/api.tvmaze.com\/episodes\/1986248"}},{"self":{"href":"https:\/\/api.tvmaze.com\/episodes\/1974421"}},{"self":{"href":"https:\/\/api.tvmaze.com\/episodes\/1974422"}},{"self":{"href":"https:\/\/api.tvmaze.com\/episodes\/2051045"}},{"self":{"href":"https:\/\/api.tvmaze.com\/episodes\/1971056"}},{"self":{"href":"https:\/\/api.tvmaze.com\/episodes\/1977832"}},{"self":{"href":"https:\/\/api.tvmaze.com\/episodes\/1977833"}},{"self":{"href":"https:\/\/api.tvmaze.com\/episodes\/1977834"}},{"self":{"href":"https:\/\/api.tvmaze.com\/episodes\/1977835"}},{"self":{"href":"https:\/\/api.tvmaze.com\/episodes\/1977836"}},{"self":{"href":"https:\/\/api.tvmaze.com\/episodes\/1977837"}},{"self":{"href":"https:\/\/api.tvmaze.com\/episodes\/1977838"}},{"self":{"href":"https:\/\/api.tvmaze.com\/episodes\/1977839"}},{"self":{"href":"https:\/\/api.tvmaze.com\/episodes\/1977840"}},{"self":{"href":"https:\/\/api.tvmaze.com\/episodes\/1985631"}},{"self":{"href":"https:\/\/api.tvmaze.com\/episodes\/1982428"}},{"self":{"href":"https:\/\/api.tvmaze.com\/episodes\/1967929"}},{"self":{"href":"https:\/\/api.tvmaze.com\/episodes\/1986023"}},{"self":{"href":"https:\/\/api.tvmaze.com\/episodes\/1970767"}},{"self":{"href":"https:\/\/api.tvmaze.com\/episodes\/1983278"}},{"self":{"href":"https:\/\/api.tvmaze.com\/episodes\/1971207"}},{"self":{"href":"https:\/\/api.tvmaze.com\/episodes\/1971208"}},{"self":{"href":"https:\/\/api.tvmaze.com\/episodes\/1971209"}},{"self":{"href":"https:\/\/api.tvmaze.com\/episodes\/1971210"}},{"self":{"href":"https:\/\/api.tvmaze.com\/episodes\/1971211"}},{"self":{"href":"https:\/\/api.tvmaze.com\/episodes\/1991659"}},{"self":{"href":"https:\/\/api.tvmaze.com\/episodes\/1976036"}},{"self":{"href":"https:\/\/api.tvmaze.com\/episodes\/1976037"}},{"self":{"href":"https:\/\/api.tvmaze.com\/episodes\/1976197"}},{"self":{"href":"https:\/\/api.tvmaze.com\/episodes\/1976198"}},{"self":{"href":"https:\/\/api.tvmaze.com\/episodes\/1977640"}},{"self":{"href":"https:\/\/api.tvmaze.com\/episodes\/1977641"}},{"self":{"href":"https:\/\/api.tvmaze.com\/episodes\/1978780"}},{"self":{"href":"https:\/\/api.tvmaze.com\/episodes\/1986074"}},{"self":{"href":"https:\/\/api.tvmaze.com\/episodes\/1987252"}},{"self":{"href":"https:\/\/api.tvmaze.com\/episodes\/1987253"}},{"self":{"href":"https:\/\/api.tvmaze.com\/episodes\/1987323"}},{"self":{"href":"https:\/\/api.tvmaze.com\/episodes\/1987324"}},{"self":{"href":"https:\/\/api.tvmaze.com\/episodes\/1987325"}},{"self":{"href":"https:\/\/api.tvmaze.com\/episodes\/1987808"}},{"self":{"href":"https:\/\/api.tvmaze.com\/episodes\/1988052"}},{"self":{"href":"https:\/\/api.tvmaze.com\/episodes\/1988053"}},{"self":{"href":"https:\/\/api.tvmaze.com\/episodes\/1988054"}},{"self":{"href":"https:\/\/api.tvmaze.com\/episodes\/1988055"}},{"self":{"href":"https:\/\/api.tvmaze.com\/episodes\/1988056"}},{"self":{"href":"https:\/\/api.tvmaze.com\/episodes\/1988057"}},{"self":{"href":"https:\/\/api.tvmaze.com\/episodes\/1988058"}},{"self":{"href":"https:\/\/api.tvmaze.com\/episodes\/1988059"}},{"self":{"href":"https:\/\/api.tvmaze.com\/episodes\/2024915"}},{"self":{"href":"https:\/\/api.tvmaze.com\/episodes\/2079007"}},{"self":{"href":"https:\/\/api.tvmaze.com\/episodes\/2079008"}},{"self":{"href":"https:\/\/api.tvmaze.com\/episodes\/2079009"}},{"self":{"href":"https:\/\/api.tvmaze.com\/episodes\/2149144"}},{"self":{"href":"https:\/\/api.tvmaze.com\/episodes\/2197282"}},{"self":{"href":"https:\/\/api.tvmaze.com\/episodes\/2197595"}},{"self":{"href":"https:\/\/api.tvmaze.com\/episodes\/2211136"}},{"self":{"href":"https:\/\/api.tvmaze.com\/episodes\/2318104"}},{"self":{"href":"https:\/\/api.tvmaze.com\/episodes\/1991534"}},{"self":{"href":"https:\/\/api.tvmaze.com\/episodes\/1984682"}},{"self":{"href":"https:\/\/api.tvmaze.com\/episodes\/1977736"}},{"self":{"href":"https:\/\/api.tvmaze.com\/episodes\/1969062"}},{"self":{"href":"https:\/\/api.tvmaze.com\/episodes\/2005524"}},{"self":{"href":"https:\/\/api.tvmaze.com\/episodes\/1977577"}},{"self":{"href":"https:\/\/api.tvmaze.com\/episodes\/2036538"}},{"self":{"href":"https:\/\/api.tvmaze.com\/episodes\/1979360"}},{"self":{"href":"https:\/\/api.tvmaze.com\/episodes\/1977412"}},{"self":{"href":"https:\/\/api.tvmaze.com\/episodes\/1987074"}},{"self":{"href":"https:\/\/api.tvmaze.com\/episodes\/1978063"}},{"self":{"href":"https:\/\/api.tvmaze.com\/episodes\/2156738"}},{"self":{"href":"https:\/\/api.tvmaze.com\/episodes\/1972712"}},{"self":{"href":"https:\/\/api.tvmaze.com\/episodes\/2152585"}}]